{
  "blogs": [
    {
      "id": 1,
      "title": "The Future of Web Design: Trends to Watch in 2025",
      "slug": "future-of-web-design-2025",
      "category": "design",
      "description": "Explore the emerging trends shaping web design this year, from AI-powered personalization to immersive interactive experiences.",
      "image": "/images/blogs/blog1.jpg",
      "author": "Sujan",
      "date": "2025-01-15",
      "readTime": "8 min read",
      "content": "Web design is evolving faster than ever, and 2025 stands out as a true landmark year for innovation, creativity, and technology. Rapid advancements in artificial intelligence, immersive digital technologies, and deep user behavior analysis have completely transformed how designers and developers create modern experiences. What was considered cutting-edge just a few years ago is now the new normal, and user expectations continue to rise as digital products become more integrated into everyday life. A modern website is no longer just a collection of pages — it is a fully interactive, intelligent platform that responds, adapts, and evolves with its users. Artificial intelligence has moved far beyond basic automation and simple recommendations. In 2025, AI is deeply embedded into the core of web design and development. Websites and web applications can now analyze user behavior in real time, including browsing history, interaction patterns, device type, interests, location, and preferences. This information is processed instantly to customize content and interface elements for each visitor. This advanced level of personalization allows layouts, typography, visuals, and even navigation to dynamically adjust based on an individual’s profile, turning a single website into a personalized experience for every user.\n\nStatic web pages are quickly becoming a thing of the past. In 2025, users expect visually rich, dynamic, and highly interactive digital environments that feel alive and emotionally engaging. This has made immersive storytelling, motion design, real-time effects, and three-dimensional environments essential elements in modern web experiences. Technologies such as WebGL, Three.js, WebGPU, and advanced animation libraries now enable designers to create complex 3D visuals and interactive environments directly in the browser. These tools are used widely across portfolios, online stores, virtual tours, education platforms, and product showcases. Features like parallax scrolling, scroll-based storytelling, interactive backgrounds, and motion-driven navigation add realism and depth. This level of immersion not only keeps users engaged for longer but also strengthens brand identity, emotional connection, and long-term memorability in an increasingly competitive digital landscape.\n\nAccessibility in 2025 is no longer optional — it is a fundamental responsibility. Modern designers and developers now place inclusivity at the center of every creative and technical decision. With stricter WCAG guidelines and a stronger global awareness of digital equity, websites must now ensure that people of all abilities can access content easily and interact without barriers. This includes using proper color contrast, readable typography, structured layouts, alternative text for images, keyboard navigation, and full compatibility with screen readers. More advanced features, such as voice navigation, real-time captions, translation support, and adaptive interfaces for cognitive and physical needs, are also becoming common. Alongside accessibility, sustainability has become a core focus. As more of the world moves online, designers are prioritizing efficient coding practices, compressed media, optimized assets, and performance-focused architectures to reduce energy consumption. Techniques like lazy loading, server-side rendering, and lightweight design systems reduce both carbon impact and loading time, creating websites that are not only eco-friendly, but also faster, smoother, and more user-friendly.\n\nThe rise of no-code and low-code platforms has transformed who can build for the web, allowing designers, entrepreneurs, creators, and students to turn ideas into reality without deep programming expertise. These tools speed up development, simplify prototyping, and encourage rapid experimentation, while traditional coding continues to power complex, customized systems. At the same time, the role of the web designer has evolved into that of a multi-skilled professional who understands design psychology, frontend logic, AI integration, accessibility standards, performance optimization, and data-driven decision-making. The future of web design goes far beyond aesthetics — it is about building intelligent, inclusive, sustainable, and emotionally engaging digital experiences. Those who continue to learn, adapt, and explore new technologies will define the next generation of the web and shape how people interact with the digital world in the years to come."
    },

    {
      "id": 2,
      "title": "Mastering User Experience: A Complete Guide to UX Design",
      "slug": "mastering-user-experience-ux-design",
      "category": "ux",
      "description": "Learn the fundamentals of creating user-centered designs that solve real problems and delight your users.",
      "image": "/images/blogs/blog2.jpg",
      "author": "Sujan",
      "date": "2025-01-08",
      "readTime": "12 min read",
      "content": "User Experience (UX) design is the backbone of every successful digital product. It blends psychology, creativity, technology, research, and strategy into one powerful discipline focused on people. In today’s fast-paced digital world, users are no longer patient with confusing interfaces or complicated navigation. Their first interaction with a website or application determines whether they trust it or abandon it. Every button, animation, color, message, and transition contributes to how a user feels. When UX is done correctly, users feel confident, comfortable, and in control. When it is done poorly, frustration and confusion take over, destroying trust and engagement.\n\nEffective UX design begins with a deep understanding of users and their real-life challenges. Designers perform detailed research, including interviews, surveys, behavior tracking, and usability testing, to understand user expectations and pain points. This information is used to create detailed personas and journey maps that represent the emotional and functional experience of users at every stage. Instead of designing based on assumptions, designers rely on real data. The UX design journey includes research, ideation, wireframing, interface design, prototyping, and testing. Each stage builds on the previous one, and continuous feedback allows the experience to be refined until it becomes natural and intuitive.\n\nStrong UX follows fundamental principles. Simplicity ensures clarity, while consistency builds familiarity and confidence. Accessibility ensures everyone, regardless of ability, can use the product. Clear feedback allows users to understand their progress and actions. Performance ensures smooth interactions without delays. Tools like Figma, Sketch, Adobe XD, and Framer bring designs to life, but true excellence in UX comes from empathy, critical thinking, user understanding, and continuous iteration.\n\nUX designers do not work alone. They collaborate with developers, marketers, product managers, and business leaders. Communication, adaptability, and data-driven reasoning are just as important as creativity. Even small improvements — such as reducing friction in checkout flows or simplifying sign-up forms — can dramatically increase conversions and user satisfaction. Ultimately, UX design is about improving human experiences, making lives easier, and creating meaningful digital solutions that serve both users and businesses."
    },

    {
      "id": 3,
      "title": "Building Scalable Design Systems: Best Practices and Strategies",
      "slug": "building-scalable-design-systems",
      "category": "design-systems",
      "description": "Discover how to create and maintain design systems that grow with your organization.",
      "image": "/images/blogs/blog3.jpg",
      "author": "Sujan",
      "date": "2024-12-28",
      "readTime": "10 min read",
      "content": "Design systems have become a critical foundation for building consistent, scalable, and efficient digital products in modern organizations. As applications grow more complex and teams expand across multiple departments and locations, maintaining visual, functional, and brand consistency becomes extremely challenging. Without a structured system in place, design decisions become fragmented, development time increases, and the overall user experience suffers. A well-built design system solves these problems by creating a shared language between designers and developers, providing a clear framework for decision-making, and serving as a central source of truth for all design and interface-related elements. It is more than just a simple library of components — it is a living, evolving structure that grows and adapts as your product, users, and business goals change over time.\n\nAt its core, a design system is made up of multiple interconnected layers. These layers include design tokens such as color palettes, typography systems, spacing scales, grid structures, and animation guidelines that establish the visual identity of a product. On top of these tokens sit reusable UI components like buttons, input fields, cards, modals, navigation bars, dropdowns, alerts, and many more. These components are then organized into higher-level patterns that solve common design challenges and define consistent user flows across the product. Comprehensive documentation plays a critical role in this process. Clear guidelines, usage examples, and best practices explain not only how to use each element, but also when and why it should be used. This ensures that every designer and developer, regardless of their experience level, can follow the same standards. As a result, confusion is reduced, collaboration becomes smoother, and product quality improves dramatically across all touchpoints.\n\nThe process of building a successful design system usually begins with a detailed audit of existing designs, codebases, and user interfaces. This helps teams identify common components, inconsistencies, and repeated patterns that can be standardized. Instead of trying to create a complete system all at once, it is more effective to start with the most important and frequently used elements, such as typography rules, color systems, buttons, and form components. Once these core building blocks are established, the system can be gradually expanded based on real-world product needs and evolving requirements. However, creating the system is only the beginning. Continuous maintenance is essential. A design system requires strong governance, clear ownership, version control, feedback loops, and regular updates. Teams must define who is responsible for approving changes, adding new components, and maintaining quality over time. Without proper management, even the best design system can quickly become outdated or inconsistent.\n\nModern tools play a significant role in supporting and maintaining design systems at scale. Figma and other collaborative design tools allow teams to create, test, and share design components in real time. Storybook provides a powerful environment for documenting and visually testing UI components in isolation, which is extremely useful for developers. Version control platforms such as GitHub help manage updates, track changes, and enable collaboration across large teams. When all of these tools are used together effectively, a design system becomes deeply integrated into the workflow of an organization. The long-term benefits are substantial: faster development cycles, reduced errors, improved onboarding for new team members, stronger brand consistency, and better collaboration between designers and developers. In the end, a well-implemented design system is not just a design asset — it is a strategic investment that strengthens the entire product development process and supports sustainable growth in the digital future."
    }
  ]
}
